methodnetworkscan/__init__.py
methodnetworkscan/core/__init__.py
methodnetworkscan/core/datetime_utils.py
methodnetworkscan/core/enum.py
methodnetworkscan/core/pydantic_utilities.py
methodnetworkscan/core/serialization.py
methodnetworkscan/py.typed
methodnetworkscan/resources/__init__.py
methodnetworkscan/resources/common/__init__.py
methodnetworkscan/resources/common/resources/__init__.py
methodnetworkscan/resources/common/resources/common/__init__.py
methodnetworkscan/resources/common/resources/common/protocol_type.py
methodnetworkscan/resources/common/resources/common/transport_type.py
methodnetworkscan/resources/common/resources/protocol/__init__.py
methodnetworkscan/resources/common/resources/protocol/resources/__init__.py
methodnetworkscan/resources/common/resources/protocol/resources/ard/__init__.py
methodnetworkscan/resources/common/resources/protocol/resources/ard/ard_server_info.py
methodnetworkscan/resources/common/resources/protocol/resources/atg/__init__.py
methodnetworkscan/resources/common/resources/protocol/resources/atg/atg_server_info.py
methodnetworkscan/resources/common/resources/protocol/resources/bgp/__init__.py
methodnetworkscan/resources/common/resources/protocol/resources/bgp/bgp_server_info.py
methodnetworkscan/resources/common/resources/protocol/resources/dcerpc/__init__.py
methodnetworkscan/resources/common/resources/protocol/resources/dcerpc/dcerpc_server_info.py
methodnetworkscan/resources/common/resources/protocol/resources/dns/__init__.py
methodnetworkscan/resources/common/resources/protocol/resources/dns/dns_server_info.py
methodnetworkscan/resources/common/resources/protocol/resources/fgfm/__init__.py
methodnetworkscan/resources/common/resources/protocol/resources/fgfm/fgfm_server_info.py
methodnetworkscan/resources/common/resources/protocol/resources/fins/__init__.py
methodnetworkscan/resources/common/resources/protocol/resources/fins/fins_server_info.py
methodnetworkscan-0.0.121.dist-info/METADATA
methodnetworkscan-0.0.121.dist-info/WHEEL
methodnetworkscan-0.0.121.dist-info/RECORD
